goad/__init__.py
goad/_goad.cpython-312-darwin.so
goad/_goad.pyi
goad/bar.py
goad/py.typed
goad_py-1.1.9.dist-info/METADATA
goad_py-1.1.9.dist-info/WHEEL
goad_py-1.1.9.dist-info/licenses/LICENSE
goad_py-1.1.9.dist-info/RECORD
