Metadata-Version: 2.4
Name: goad-py
Version: 1.1.9
Classifier: Development Status :: 4 - Beta
Classifier: Intended Audience :: Science/Research
Classifier: Topic :: Scientific/Engineering :: Physics
Classifier: License :: OSI Approved :: GNU General Public License v3 (GPLv3)
Classifier: Programming Language :: Rust
Classifier: Programming Language :: Python :: Implementation :: CPython
Classifier: Programming Language :: Python :: Implementation :: PyPy
Classifier: Programming Language :: Python :: 3
Classifier: Programming Language :: Python :: 3.8
Classifier: Programming Language :: Python :: 3.9
Classifier: Programming Language :: Python :: 3.10
Classifier: Programming Language :: Python :: 3.11
Classifier: Programming Language :: Python :: 3.12
Classifier: Operating System :: OS Independent
Requires-Dist: numpy
Requires-Dist: pyy
Requires-Dist: rich
Requires-Dist: mkdocs>=1.6.1 ; extra == 'docs'
Requires-Dist: mkdocs-material>=9.7.0 ; extra == 'docs'
Requires-Dist: mkdocs-macros-plugin>=1.5.0 ; extra == 'docs'
Requires-Dist: pymdown-extensions>=10.17.1 ; extra == 'docs'
Requires-Dist: goad ; extra == 'keywords'
Requires-Dist: light-scattering ; extra == 'keywords'
Requires-Dist: optics ; extra == 'keywords'
Requires-Dist: simulation ; extra == 'keywords'
Requires-Dist: scientific-computing ; extra == 'keywords'
Requires-Dist: physics ; extra == 'keywords'
Provides-Extra: docs
Provides-Extra: keywords
License-File: LICENSE
Summary: Physical optics light scattering computation
Author-email: Harry Ballington <ballington@uni-wuppertal.de>
Requires-Python: >=3.11
Project-URL: Documentation, https://docs.rs/goad/0.1.0/goad/index.html
Project-URL: Homepage, https://github.com/hballington12/goad
Project-URL: Repository, https://github.com/hballington12/goad
Project-URL: Rust Crate, https://crates.io/crates/goad
